MANIFEST.in
setup.py
django_responsive_admin.egg-info/PKG-INFO
django_responsive_admin.egg-info/SOURCES.txt
django_responsive_admin.egg-info/dependency_links.txt
django_responsive_admin.egg-info/top_level.txt
responsive_admin/__init__.py
responsive_admin/__init__.pyc
responsive_admin/conf/__init__.py
responsive_admin/conf/__init__.pyc
responsive_admin/conf/settings.py
responsive_admin/conf/settings.pyc
responsive_admin/static/admin/css/admin.css
responsive_admin/static/admin/css/kube.css
responsive_admin/static/admin/img/glyphicons-halflings-white.png
responsive_admin/static/admin/img/glyphicons-halflings.png
responsive_admin/static/admin/img/logo-140x140.png
responsive_admin/static/admin/js/actions.js
responsive_admin/templates/admin/404.html
responsive_admin/templates/admin/500.html
responsive_admin/templates/admin/actions.html
responsive_admin/templates/admin/app_index.html
responsive_admin/templates/admin/base.html
responsive_admin/templates/admin/base_site.html
responsive_admin/templates/admin/change_form.html
responsive_admin/templates/admin/change_list.html
responsive_admin/templates/admin/change_list_results.html
responsive_admin/templates/admin/date_hierarchy.html
responsive_admin/templates/admin/delete_confirmation.html
responsive_admin/templates/admin/delete_selected_confirmation.html
responsive_admin/templates/admin/filter.html
responsive_admin/templates/admin/index.html
responsive_admin/templates/admin/invalid_setup.html
responsive_admin/templates/admin/login.html
responsive_admin/templates/admin/object_history.html
responsive_admin/templates/admin/pagination.html
responsive_admin/templates/admin/prepopulated_fields_js.html
responsive_admin/templates/admin/search_form.html
responsive_admin/templates/admin/submit_line.html
responsive_admin/templates/admin/auth/user/add_form.html
responsive_admin/templates/admin/auth/user/change_password.html
responsive_admin/templates/admin/edit_inline/stacked.html
responsive_admin/templates/admin/edit_inline/tabular.html
responsive_admin/templates/admin/includes/fieldset.html
responsive_admin/templates/registration/logged_out.html
responsive_admin/templates/registration/password_change_done.html
