Metadata-Version: 1.1
Name: django-responsive-admin
Version: 0.2.8
Summary: A responsive admin for Django using Kube CSS
Home-page: https://github.com/pdr/django-responsive-admin
Author: Pierre Drescher
Author-email: pierre.drescher@gmail.com
License: MIT
Platform: UNKNOWN
Classifier: Environment :: Web Environment
Classifier: Intended Audience :: Developers
Classifier: Development Status :: 4 - Beta
Classifier: License :: OSI Approved :: MIT License
Classifier: Operating System :: OS Independent
Classifier: Programming Language :: Python
Classifier: Topic :: Utilities
